examples/__init__.py
examples/pdtable_demo.py
examples/test_pdtable_demo.py
pdtable/__init__.py
pdtable/auxiliary.py
pdtable/frame.py
pdtable/proxy.py
pdtable/store.py
pdtable/table_metadata.py
pdtable/table_origin.py
pdtable/utils.py
pdtable/demo/__init__.py
pdtable/demo/directive_handlers.py
pdtable/demo/unit_converter.py
pdtable/io/__init__.py
pdtable/io/_excel_openpyxl.py
pdtable/io/_excel_write_helper.py
pdtable/io/_excel_xlsxwriter.py
pdtable/io/_json.py
pdtable/io/_represent.py
pdtable/io/csv.py
pdtable/io/excel.py
pdtable/io/json.py
pdtable/io/load/__init__.py
pdtable/io/load/_loaders.py
pdtable/io/load/_orchestrators.py
pdtable/io/load/_protocol.py
pdtable/io/load/_tree.py
pdtable/io/parsers/__init__.py
pdtable/io/parsers/blocks.py
pdtable/io/parsers/columns.py
pdtable/io/parsers/fixer.py
pdtable/test/__init__.py
pdtable/test/conftest.py
pdtable/test/test_ancillary_blocks.py
pdtable/test/test_pdtable.py
pdtable/test/test_store.py
pdtable/test/test_table_origin.py
pdtable/test/test_units.py
pdtable/test/input/__init__.py
pdtable/test/io/__init__.py
pdtable/test/io/test_csv.py
pdtable/test/io/test_excel.py
pdtable/test/io/test_formatting.py
pdtable/test/io/test_json.py
pdtable/test/io/test_load.py
pdtable/test/io/test_read_bundle_from_csv.py
pdtable/test/io/test_read_csv_fixer.py
pdtable/test/io/input/__init__.py
pdtable/test/io/input/with_errors/__init__.py
pdtable/test/io/input/with_errors/auto_fixed.py
pdtable/test/io/parsers/__init__.py
pdtable/test/io/parsers/test_block_parsers.py
pdtable/test/io/parsers/test_blocks.py
pdtable/test/io/parsers/test_column_parsers.py
pdtable/units/__init__.py
pdtable/units/pint.py
pdtable-1.0.1.dist-info/LICENSE.txt
pdtable-1.0.1.dist-info/METADATA
pdtable-1.0.1.dist-info/WHEEL
pdtable-1.0.1.dist-info/top_level.txt
pdtable-1.0.1.dist-info/RECORD
