Metadata-Version: 2.1
Name: pdtable
Version: 1.0.1
Summary: Reads and writes data stored in StarTable format; and stores table data inmemory as a Pandas data frame for easy manipulation.
Home-page: https://github.com/startable/pdtable/
Author: Jean-François Corbett
Author-email: jeaco@orsted.dk
License: BSD-3-Clause
Keywords: startable data-structure file-format table dataframe json
Classifier: Development Status :: 3 - Alpha
Classifier: Intended Audience :: Developers
Classifier: License :: OSI Approved :: BSD License
Classifier: Programming Language :: Python :: 3
Requires-Python: >=3.7
License-File: LICENSE.txt
Requires-Dist: numpy
Requires-Dist: pandas
